sim_sci_test_monorepo/__init__.py
sim_sci_test_monorepo/public_health/__init__.py
sim_sci_test_monorepo/public_health/_version.py
sim_sci_test_monorepo/public_health/models.py
sim_sci_test_monorepo_public_health-0.0.8.dist-info/METADATA
sim_sci_test_monorepo_public_health-0.0.8.dist-info/WHEEL
sim_sci_test_monorepo_public_health-0.0.8.dist-info/top_level.txt
sim_sci_test_monorepo_public_health-0.0.8.dist-info/RECORD
